mojodojo/__init__.py
mojodojo/__version__.py
mojodojo-0.0.3.dist-info/LICENSE
mojodojo-0.0.3.dist-info/METADATA
mojodojo-0.0.3.dist-info/WHEEL
mojodojo-0.0.3.dist-info/top_level.txt
mojodojo-0.0.3.dist-info/RECORD
