Metadata-Version: 2.1
Name: mojodojo
Version: 0.0.3
Summary: The Mojo Dojo
Home-page: https://github.com/trevorhobenshield/mojodojo
Author: Trevor Hobenshield
Author-email: trevorhobenshield@gmail.com
License: MIT
Keywords: mojo dojo
Classifier: Intended Audience :: Developers
Classifier: Natural Language :: English
Classifier: Operating System :: Unix
Classifier: Operating System :: MacOS :: MacOS X
Classifier: Operating System :: Microsoft :: Windows
Classifier: Programming Language :: Python
Classifier: Programming Language :: Python :: 3
Classifier: Programming Language :: Python :: 3.10
Classifier: Programming Language :: Python :: 3.11
Classifier: Programming Language :: Python :: 3.12
Classifier: Topic :: Internet :: WWW/HTTP
Classifier: Topic :: Software Development :: Libraries
Classifier: Topic :: Software Development :: Libraries :: Python Modules
Requires-Python: >=3.10.10
License-File: LICENSE
